src/__init__.py
src/cli.py
src/models.py
src/translator.py
tests/conftest.py
tests/test_cli.py
tests/test_models.py
tests/test_translator.py
xcstrings_translator-1.0.0.dist-info/licenses/LICENSE
xcstrings_translator-1.0.0.dist-info/METADATA
xcstrings_translator-1.0.0.dist-info/WHEEL
xcstrings_translator-1.0.0.dist-info/entry_points.txt
xcstrings_translator-1.0.0.dist-info/top_level.txt
xcstrings_translator-1.0.0.dist-info/RECORD
