Metadata-Version: 2.4
Name: xcstrings-translator
Version: 1.0.0
Summary: Translate Apple Localizable.xcstrings files using Claude AI
Author-email: Justin Lanfermann <Justin@Lanfermann.dev>
License-Expression: MIT
Project-URL: Homepage, https://github.com/jaylann/XCStringsTranslator
Project-URL: Repository, https://github.com/jaylann/XCStringsTranslator
Project-URL: Issues, https://github.com/jaylann/XCStringsTranslator/issues
Keywords: xcstrings,localization,translation,apple,ios,macos,i18n,claude,ai
Classifier: Development Status :: 4 - Beta
Classifier: Intended Audience :: Developers
Classifier: Programming Language :: Python :: 3
Classifier: Programming Language :: Python :: 3.11
Classifier: Programming Language :: Python :: 3.12
Classifier: Topic :: Software Development :: Localization
Requires-Python: >=3.11
License-File: LICENSE
Requires-Dist: pydantic>=2.0.0
Requires-Dist: pydantic-ai>=0.0.14
Requires-Dist: pydantic-ai-slim[anthropic,google,openai]>=0.0.14
Requires-Dist: typer[all]>=0.9.0
Requires-Dist: rich>=13.0.0
Provides-Extra: dev
Requires-Dist: pytest>=7.0.0; extra == "dev"
Requires-Dist: black>=23.0.0; extra == "dev"
Requires-Dist: ruff>=0.1.0; extra == "dev"
Dynamic: license-file
